{"name":"Takashi Abiko","tagline":"Resume","body":"# RELEVANT COURSEWORK\r\n### University of Denver\r\n* Environmental Applications\r\n* GIS and Natural Hazards\r\n* Cartographic Design\r\n* Remote Sensing\r\n* Digital Image Processing\r\n* Internet Mapping\r\n\r\n### California State University, Fresno\r\n* Petrology\r\n* Sedimentology\r\n* Mineralogy\r\n* Stratigraphy\r\n* Tectonics of Orogenic Belts\r\n* Landslides, Structural Geology\r\n* Analysis Methods\r\n* Field Methods\r\n\r\n### University of Colorado, Colorado Springs\r\n* Introduction to GIS\r\n* Biogeography\r\n* Physical Geography\r\n* Seminar I - Paradigm Shifts in Geography\r\n\r\n#[Graduate Research Next](http://tabiko.github.io/Graduate-Research/)\r\n##[Back](http://tabiko.github.io/Work-Experience/)\r\n###[Takashi Abiko Home](http://tabiko.github.io/)","google":"","note":"Don't delete this file! It's used internally to help with page regeneration."}